<Properties StartupConfiguration="{DD4E2E22-0A5D-4C02-B243-CEC656954AB9}|Default">
  <MonoDevelop.Ide.Workbench ActiveDocument="homework2/Program.cs">
    <Files>
      <File FileName="homework2/Program.cs" Line="23" Column="53" />
    </Files>
    <Pads>
      <Pad Id="ProjectPad">
        <State name="__root__">
          <Node name="homework2" expanded="True">
            <Node name="homework2" expanded="True" />
          </Node>
        </State>
      </Pad>
      <Pad Id="MonoDevelop.Debugger.WatchPad">
        <State />
      </Pad>
    </Pads>
  </MonoDevelop.Ide.Workbench>
  <MonoDevelop.Ide.DebuggingService.Breakpoints>
    <BreakpointStore>
      <Breakpoint file="/Users/tarasivanov/ОП дз/op-kp23-Ivanov/homework2/homework2/Program.cs" relfile="homework2/Program.cs" line="23" column="1" />
    </BreakpointStore>
  </MonoDevelop.Ide.DebuggingService.Breakpoints>
  <MultiItemStartupConfigurations />
  <MonoDevelop.Ide.Workspace ActiveConfiguration="Debug" />
  <MonoDevelop.Ide.ItemProperties.homework2 PreferredExecutionTarget="MonoDevelop.Default" />
  <MonoDevelop.Ide.DebuggingService.PinnedWatches />
</Properties>